graph_envs/MultiCast.py
graph_envs/ShortestPath.py
graph_envs/__init__.py
graph_envs-0.0.65.dist-info/LICENSE
graph_envs-0.0.65.dist-info/METADATA
graph_envs-0.0.65.dist-info/WHEEL
graph_envs-0.0.65.dist-info/top_level.txt
graph_envs-0.0.65.dist-info/RECORD
