Metadata-Version: 2.1
Name: graph-envs
Version: 0.0.65
Summary: Graph Reinforcement Learning Environments
Home-page: https://github.com/teshnizi/GraphEnvs
Author: Teshnizi
Author-email: teshnizi@stanford.edu
Project-URL: Bug Tracker, https://github.com/teshnizi/GraphEnvs/issues
Classifier: Programming Language :: Python :: 3
Classifier: License :: OSI Approved :: MIT License
Classifier: Operating System :: OS Independent
Requires-Python: >=3.6
License-File: LICENSE
